MANIFEST.in
README.rst
setup.cfg
setup.py
docs/CREDITS.txt
docs/HISTORY.txt
docs/LICENSE.GPL
docs/LICENSE.txt
src/collective/__init__.py
src/collective.grok.egg-info/PKG-INFO
src/collective.grok.egg-info/SOURCES.txt
src/collective.grok.egg-info/dependency_links.txt
src/collective.grok.egg-info/entry_points.txt
src/collective.grok.egg-info/namespace_packages.txt
src/collective.grok.egg-info/not-zip-safe
src/collective.grok.egg-info/requires.txt
src/collective.grok.egg-info/top_level.txt
src/collective/grok/__init__.py
src/collective/grok/configure.zcml
src/collective/grok/meta.py
src/collective/grok/meta.zcml
src/collective/grok/testing.py
src/collective/grok/gs/__init__.py
src/collective/grok/gs/export.py
src/collective/grok/gs/import_.py
src/collective/grok/gs/profile.py
src/collective/grok/gs/upgrade.py
src/collective/grok/i18n/__init__.py
src/collective/grok/i18n/translations.py
src/collective/grok/tests/__init__.py
src/collective/grok/tests/test_gs.py
src/collective/grok/tests/test_i18n.py
src/collective/grok/tests/gs/__init__.py
src/collective/grok/tests/gs/export.py
src/collective/grok/tests/gs/import_.py
src/collective/grok/tests/gs/profile.py
src/collective/grok/tests/gs/profile_no_kw.py
src/collective/grok/tests/gs/upgrade.py
src/collective/grok/tests/gs/profiles/testing/metadata.xml
src/collective/grok/tests/i18n/__init__.py
src/collective/grok/tests/i18n/translations.py
src/collective/grok/tests/i18n/locales/es/LC_MESSAGES/collective.grok.tests.i18n.mo
src/collective/grok/tests/i18n/locales/es/LC_MESSAGES/collective.grok.tests.i18n.po
src/collective/grok/tests/i18n/locales/pt_BR/LC_MESSAGES/collective.grok.tests.i18n.mo
src/collective/grok/tests/i18n/locales/pt_BR/LC_MESSAGES/collective.grok.tests.i18n.po